aom_framework/__init__.py
aom_framework/protocols_pb2.py
aom_framework/protocols_pb2_grpc.py
aom_framework/services_pb2.py
aom_framework/services_pb2_grpc.py
aom_framework/agent_service/__init__.py
aom_framework/env_service/__init__.py
aom_sdk-0.0.3.dist-info/DESCRIPTION.rst
aom_sdk-0.0.3.dist-info/METADATA
aom_sdk-0.0.3.dist-info/RECORD
aom_sdk-0.0.3.dist-info/WHEEL
aom_sdk-0.0.3.dist-info/metadata.json
aom_sdk-0.0.3.dist-info/top_level.txt
