Metadata-Version: 2.0
Name: aom-sdk
Version: 0.0.3
Summary: AoM platform sdk
Home-page: https://gitlab.com/age-of-minds/aom-framework
Author: Age of Minds
Author-email: dev@ageofminds.com
License: Apache License 2.0
Platform: UNKNOWN
Requires-Dist: grpcio (>=1.19)
Requires-Dist: protobuf (>=3.7)
